{
	"info": {
		"_postman_id": "64ad4ced-4ea5-4b52-8759-07eafd149252",
		"name": "Cadastro_Clientes",
		"schema": "https://schema.getpostman.com/json/collection/v2.1.0/collection.json"
	},
	"item": [
		{
			"name": "Clientes",
			"item": [
				{
					"name": "Clientes",
					"request": {
						"method": "GET",
						"header": []
					},
					"response": []
				},
				{
					"name": "busca cliente por id",
					"request": {
						"method": "GET",
						"header": []
					},
					"response": []
				},
				{
					"name": "Adiciona Clientes",
					"request": {
						"method": "POST",
						"header": [],
						"url": {
							"raw": "http://localhost:8000/clientes",
							"protocol": "http",
							"host": [
								"localhost"
							],
							"port": "8000",
							"path": [
								"clientes"
							]
						}
					},
					"response": []
				},
				{
					"name": "Atualiza Clientes",
					"request": {
						"method": "POST",
						"header": [],
						"url": {
							"raw": "http://localhost:8000/clientes",
							"protocol": "http",
							"host": [
								"localhost"
							],
							"port": "8000",
							"path": [
								"clientes"
							]
						}
					},
					"response": []
				},
				{
					"name": "Deleta Clientes por ID",
					"request": {
						"method": "DELETE",
						"header": [],
						"url": {
							"raw": "{{url}}clientes/2",
							"host": [
								"{{url}}clientes"
							],
							"path": [
								"2"
							]
						}
					},
					"response": []
				}
			]
		},
		{
			"name": "Endereço",
			"item": [
				{
					"name": "Endereços",
					"request": {
						"method": "GET",
						"header": []
					},
					"response": []
				},
				{
					"name": "Busca endereços por id",
					"request": {
						"method": "GET",
						"header": []
					},
					"response": []
				},
				{
					"name": "Adiciona Endereços",
					"request": {
						"method": "POST",
						"header": [],
						"url": {
							"raw": "http://localhost:8000/enderecos",
							"protocol": "http",
							"host": [
								"localhost"
							],
							"port": "8000",
							"path": [
								"enderecos"
							]
						}
					},
					"response": []
				},
				{
					"name": "Atualiza Endereços",
					"request": {
						"method": "POST",
						"header": [],
						"body": {
							"mode": "urlencoded",
							"urlencoded": [
								{
									"key": "cep",
									"value": "",
									"type": "text"
								},
								{
									"key": "rua",
									"value": "",
									"type": "text"
								},
								{
									"key": "bairro",
									"value": "",
									"type": "text"
								},
								{
									"key": "cidade",
									"value": "",
									"type": "text"
								},
								{
									"key": "estado",
									"value": "",
									"type": "text"
								},
								{
									"key": "ibge",
									"value": "",
									"type": "text"
								}
							]
						},
						"url": {
							"raw": "{{url}}enderecos/1",
							"host": [
								"{{url}}enderecos"
							],
							"path": [
								"1"
							]
						}
					},
					"response": []
				},
				{
					"name": "Deleta Endereços",
					"request": {
						"method": "DELETE",
						"header": [],
						"url": {
							"raw": "{{url}}enderecos/1",
							"host": [
								"{{url}}enderecos"
							],
							"path": [
								"1"
							]
						}
					},
					"response": []
				}
			]
		}
	],
	"event": [
		{
			"listen": "prerequest",
			"script": {
				"type": "text/javascript",
				"exec": [
					""
				]
			}
		},
		{
			"listen": "test",
			"script": {
				"type": "text/javascript",
				"exec": [
					""
				]
			}
		}
	],
	"variable": [
		{
			"key": "url",
			"value": "http://localhost:8000/"
		}
	]
}